setup.py
amifinder/__init__.py
amifinder/cli.py
amifinder.egg-info/PKG-INFO
amifinder.egg-info/SOURCES.txt
amifinder.egg-info/dependency_links.txt
amifinder.egg-info/entry_points.txt
amifinder.egg-info/not-zip-safe
amifinder.egg-info/requires.txt
amifinder.egg-info/top_level.txt