Metadata-Version: 1.1
Name: amifinder
Version: 0.0.4
Summary: Command line tool to find AMI IDs for a few OS
Home-page: https://github.com/mbrannigan/amifinder
Author: mbrannigan
Author-email: mikejbrannigan@gmail.com
License: MIT
Keywords: aws,amazon web services,ami,amazon machine images,automation
Platform: UNKNOWN
Classifier: Programming Language :: Python
Classifier: Programming Language :: Python :: 2.6
Classifier: Programming Language :: Python :: 2.7
Classifier: Intended Audience :: Developers
Classifier: License :: OSI Approved :: MIT License
Classifier: Operating System :: OS Independent
Classifier: Topic :: Software Development
Classifier: Topic :: Software Development :: Libraries
Classifier: Topic :: Software Development :: Libraries :: Python Modules
Classifier: Development Status :: 4 - Beta
